[
    {
        "spl": "Besondere Lehrangebote",
        "classes": [
            "00.01 Individuelle Studien",
            "00.02 Interdisziplinäre Studien",
            "00.03 Fächerübergreifende Studienangebote",
            "00.04 Erweiterungscurricula",
            "00.05 univie: summer/winter schools",
            "00.06 DoktorandInnenzentrum",
            "00.07 Studienberechtigungsprüfung",
            "00.08 Universitätslehrgänge",
            "00.09 Zertifikatskurse"
        ]
    },
    {
        "spl": "Katholische Theologie",
        "classes": [
            "01.01 Bachelor Religionspädagogik (Schwerpunkt: Katholisch Theologische Bildung) (195 [7] - Version 2017)",
            "01.02 Bachelor Religionspädagogik (Schwerpunkt: Katholische Religionspädagogik) (195 [7] - Version 2017)",
            "01.03 Bachelor Religionspädagogik (Schwerpunkt: Religionswissenschaftliche Bildung) (195 [7] - Version 2017)",
            "01.04 Bachelor Lehramt UF Katholische Religion (193 055, 198 418)",
            "01.05 Diplom Katholische Fachtheologie (011 [3] - Version 2015)",
            "01.06 Diplom Katholische Fachtheologie (011 [4] - Version 2011) - auslaufend",
            "01.07 Master Theologische Spezialisierung (795 [2] - Version 2015)",
            "01.08 Master Religionspädagogik (Schwerpunkt: Katholische Religionspädagogik) (796 - Version 2017)",
            "01.09 Master Religionspädagogik (Schwerpunkt: Orthodoxe Religionspädagogik) (796 - Version 2017)",
            "01.10 Master Religionswissenschaft (800)",
            "01.11 Master Lehramt UF Katholische Religion (196 055, 199 518)",
            "01.12 Erweiterungscurriculum Grundlagen und Methoden der Religionswissenschaft (011 [2] - Version 2015)",
            "01.13 Erweiterungscurriculum Hauptthemen der Religionsgeschichte (012)"
        ]
    },
    {
        "spl": "Evangelische Theologie",
        "classes": [
            "02.01 Bachelor Evangelische Theologie (190 [3] - Version 2014)",
            "02.02 Bachelor Religionspädagogik (Schwerpunkt: Evangelische Religionspädagogik) (195 [6] - Version 2017)",
            "02.03 Bachelor Religionspädagogik (Schwerpunkt: Evangelische Religionspädagogik) (195 [5] - Version 2015) - auslaufend",
            "02.04 Bachelor Lehramt UF Evangelische Religion (408)",
            "02.05 Diplom Lehramt UF Evangelische Religion (043 [2] - Version 2011) - auslaufend",
            "02.06 Master Evangelische Fachtheologie (790 [2] - Version 2014)",
            "02.07 Master Religionspädagogik (Schwerpunkt: Evangelische Religionspädagogik) (796 [3] - Version 2017)",
            "02.08 Master Lehramt UF Evangelische Religion (508)",
            "02.09 Erweiterungscurriculum Die Bibel: Buch, Geschichte, Auslegung (015)",
            "02.10 Erweiterungscurriculum Christentum in der pluralen Gesellschaft (016)",
            "02.11 Blocklehrveranstaltungen der SPL 2 + 37",
            "02.12 Lehrveranstaltungen zur Vorbereitung auf Ergänzungsprüfungen",
            "02.13 Individuelles Masterstudium Evangelisch-Theologische Studien"
        ]
        
    },
    {
        "spl": "Rechtswissenschaften",
        "classes": [
            "03.01 Diplom Rechtswissenschaften (101 [4] - Version 2017)",
            "03.02 Master Wirtschaftsrecht (UL 900)",
            "03.03 Erweiterungscurriculum Einführung in die Rechtswissenschaften (031)",
            "03.04 Erweiterungscurriculum Internationales Recht (032)",
            "03.05 Erweiterungscurriculum Öffentliches Recht - Rechtsstaat, Demokratie und Verwaltung (033)",
            "03.06 Erweiterungscurriculum Privatrecht - Rechtsgestaltung in Alltag und Unternehmen (034)",
            "03.07 Erweiterungscurriculum Strafrecht und Kriminologie (035)",
            "03.08 Erweiterungscurriculum Recht im historischen, gesellschaftlichen und philosophischen Kontext (036)"
        ]
    },
    {
        "spl": "Wirtschaftswissenschaften",
        "classes": [
            "04.01 Bachelor Volkswirtschaftslehre (513 [3] - Version 2014)",
            "04.02 Bachelor Internationale Betriebswirtschaft (514 [3] - Version 2014)",
            "04.03 Bachelor Betriebswirtschaft (515 [3] - Version 2014)",
            "04.04 Bachelor Statistik (551 [3] - Version 2014)",
            "04.05 Master Volkswirtschaftslehre (913 [2] - Version 2013)",
            "04.06 Master Internationale Betriebswirtschaft (914 [3] - Version 2016)",
            "04.07 Master Betriebswirtschaft (915 [3] - Version 2016)",
            "04.08 Magister Statistik (951)",
            "04.09 Master Banking and Finance (974)",
            "04.10 Erweiterungscurriculum Entrepreneurship (046)",
            "04.11 Erweiterungscurriculum Global Corporate Management (047)",
            "04.12 Erweiterungscurriculum Grundlagen der Statistik (048)",
            "04.13 Erweiterungscurriculum Statistik: Inferenz und Datenanalyse (049)",
            "04.14 Erweiterungscurriculum Wirtschaft-Gesellschaft-Staat (540)",
            "04.15 Erweiterungscurriculum Methoden und Anwendungen der Volkswirtschaftslehre (541)",
            "04.16 Erweiterungscurriculum Grundlagen der Volkswirtschaftslehre (542)",
            "04.17 Erweiterungscurriculum Betriebswirtschaftliche Grundlagen (543)",
            "04.18 Erweiterungscurriculum Betriebswirtschaftliche Methoden (544)",
            "04.19 Erweiterungscurriculum Grundlagen der Volkswirtschaftslehre (542 [2] - Version 2020)",
            "04.20 Erweiterungscurriculum Methoden der Volkswirtschaftslehre (545)",
            "04.21 Erweiterungscurriculum Quantitative Grundlagen der Volkswirtschaftslehre (546)",
            "04.22 Lehrveranstaltungen im Sommer",
            "04.23 Master Business Analytics (977)"
        ]
    },
    {
        "spl": "Informatik und Wirtschaftsinformatik",
        "classes": [
            "05.01 Bachelor Informatik 2016 (521 [4])",
            "05.02 Bachelor Informatik 2016 (521 [4]) - Data Science",
            "05.03 Bachelor Informatik 2016 (521 [4]) - Medieninformatik",
            "05.04 Bachelor Informatik 2016 (521 [4]) - Medizininformatik",
            "05.05 Bachelor Informatik 2016 (521 [4]) - Scientific Computing",
            "05.06 Bachelor Wirtschaftsinformatik 2016 (526 [3])",
            "05.07 Bachelor Lehramt UF Informatik (193 053 [1], 198 414 [1])",
            "05.08 Master Bioinformatik (875 [1])",
            "05.09 Master Data Science (645 [1])",
            "05.10 Master Informatik (921 [1])",
            "05.11 Master Informatik (921 [1]) - Data Science",
            "05.12 Master Informatik (921 [1]) - Scientific Computing",
            "05.13 Master Medieninformatik 2016 (935 [2])",
            "05.14 Master Wirtschaftsinformatik 2016 (926 [2])",
            "05.15 Master Lehramt UF Informatik (196 053 [1], 199 514 [1])",
            "05.16 Master Informatikdidaktik (950 [1]) - auslaufend",
            "05.17 Erweiterungscurriculum (EC) Computational Thinking / Informatik (050 [1])",
            "05.18 Sonstiges Lehrangebot"
        ]
    },
    {
        "spl": "Ägyptologie, Judaistik, Urgeschichte und Historische Archäologie",
        "classes": [
            "06.01 Urgeschichte und Historische Archäologie",
            "06.02 Ägyptologie",
            "06.03 Judaistik",
            "06.04 Numismatik",
            "06.05 Interdisziplinäre Erweiterungscurricula",

        ]
    },
    {
        "spl": "Geschichte",
        "classes": [
            "07.01 Bachelor Geschichte (603 [4] - Version 2019)",
            "07.02 Bachelor Geschichte (603 [3] - Version 2012) - auslaufend",
            "07.03 Bachelor Lehramt UF Geschichte, Sozialkunde und Politische Bildung (193 050, 198 411)",
            "07.04 Diplom Lehramt UF Geschichte, Sozialkunde und Politische Bildung (190 313) - auslaufend",
            "07.05 Erweiterungscurriculum Geschichte (071)",
            "07.06 Erweiterungscurriculum Zeitgeschichte und Medien (072)",
            "07.07 Master Lehramt UF Geschichte, Sozialkunde und Politische Bildung (196 050, 199 511)",
            "07.08 Master Geschichte (803 [3] - Version 2019)",
            "07.09 Master Geschichte (803 [2] - Version 2014) - auslaufend",
            "07.10 Master Historische Hilfswissenschaften und Archivwissenschaft (804 [4] - Version 2019)",
            "07.11 Master Geschichtsforschung, Historische Hilfswissenschaften und Archivwissenschaft (804 [3] - Version 2016) - auslaufend",
            "07.12 Master Globalgeschichte & Global Studies (805 [3] - Version 2019)",
            "07.13 Master Globalgeschichte & Global Studies (805 [2] - Version 2008) - auslaufend",
            "07.14 Master Interdisziplinäre Osteuropastudien (610 [2] - Version 2019)",
            "07.15 Master Interdisziplinäre Osteuropastudien (610 [1] - Version 2015) - auslaufend",
            "07.16 Interdisziplinärer Master Zeitgeschichte und Medien (665 [2] - Version 2019)",
            "07.17 Interdisziplinärer Master Zeitgeschichte und Medien (665 [1] - Version 2016) - auslaufend"

        ]
    },
    {
        "spl": "Kunstgeschichte und Europäische Ethnologie",
        "classes": [
            "08.01 Kunstgeschichte",
            "08.02 Europäische Ethnologie",
        ]

    },
    {
        "spl": "Altertumswissenschaften",
        "classes": [
            "09.01 Alte Geschichte und Altertumskunde",
            "09.02 Byzantinistik und Neogräzistik",
            "09.03 Klassische Archäologie",
            "09.04 Klassische Philologie, Mittel- und Neulatein"
        ]
    },
    {
        "spl": "Deutsch Philologie",
        "classes": [
            "10.01 Bachelor Deutsche Philologie (617 [2] - Version 2011)",
            "10.02 Bachelor Lehramt UF Deutsch (193 045, 198 406)",
            "10.03 Master Deutsch als Fremd- und Zweitsprache (814 [2] - Version 2017)",
            "10.04 Master Deutsche Philologie (817)",
            "10.05 Master Austrian Studies - Cultures, Literatures, Languages (Österreichstudien - Kulturen, Literaturen, Sprachen) (818)",
            "10.06 Master Lehramt UF Deutsch (196 045, 199 506)",
            "10.07 Erweiterungscurriculum Deutsche Philologie im Überblick (104)",
            "10.08 Erweiterungscurriculum Deutsche Sprache (105)",
            "10.09 Erweiterungscurriculum Deutschsprachige Literatur (106)",
            "10.10 Erweiterungscurriculum Akademische Schreibkompetenz entwickeln, vermitteln und beforschen - Ausbildung von SchreibmentorInnen (107)",
            "10.11 Lehrveranstaltungen mit Genderschwerpunkt",
            "10.12 Fachtutorien"
        ]
    }
]